odoo8_addon_account_payment_include_draft_move-8.0.1.0.0-py2.7-nspkg.pth
odoo_addons/account_payment_include_draft_move/__openerp__.py
odoo_addons/account_payment_include_draft_move/__init__.py
odoo_addons/account_payment_include_draft_move/README.rst
odoo_addons/account_payment_include_draft_move/wizard/payment_order_create.py
odoo_addons/account_payment_include_draft_move/wizard/__init__.py
odoo_addons/account_payment_include_draft_move/static/description/icon.png
odoo8_addon_account_payment_include_draft_move-8.0.1.0.0.dist-info/top_level.txt
odoo8_addon_account_payment_include_draft_move-8.0.1.0.0.dist-info/WHEEL
odoo8_addon_account_payment_include_draft_move-8.0.1.0.0.dist-info/RECORD
odoo8_addon_account_payment_include_draft_move-8.0.1.0.0.dist-info/metadata.json
odoo8_addon_account_payment_include_draft_move-8.0.1.0.0.dist-info/DESCRIPTION.rst
odoo8_addon_account_payment_include_draft_move-8.0.1.0.0.dist-info/METADATA
odoo8_addon_account_payment_include_draft_move-8.0.1.0.0.dist-info/namespace_packages.txt
