Metadata-Version: 2.0
Name: odoo8-addon-account-payment-include-draft-move
Version: 8.0.1.0.0
Summary: Account Payment Draft Move
Home-page: http://www.acsone.eu
Author: UNKNOWN
Author-email: UNKNOWN
License: UNKNOWN
Platform: UNKNOWN
Requires-Dist: odoo (<9.0a,>=8.0a)
Requires-Dist: odoo8-addon-account-banking-payment-export
Classifier: Programming Language :: Python :: 2.7
Classifier: Framework :: Odoo
